odoo/addons/pos_order_split_invoice/README.rst
odoo/addons/pos_order_split_invoice/__init__.py
odoo/addons/pos_order_split_invoice/__manifest__.py
odoo/addons/pos_order_split_invoice/i18n/it.po
odoo/addons/pos_order_split_invoice/i18n/pos_order_split_invoice.pot
odoo/addons/pos_order_split_invoice/models/__init__.py
odoo/addons/pos_order_split_invoice/models/account_move.py
odoo/addons/pos_order_split_invoice/models/pos_order.py
odoo/addons/pos_order_split_invoice/models/pos_order_line.py
odoo/addons/pos_order_split_invoice/models/pos_session.py
odoo/addons/pos_order_split_invoice/models/product_pricelist.py
odoo/addons/pos_order_split_invoice/readme/CONFIGURE.md
odoo/addons/pos_order_split_invoice/readme/CONTRIBUTORS.md
odoo/addons/pos_order_split_invoice/readme/DESCRIPTION.md
odoo/addons/pos_order_split_invoice/readme/USAGE.md
odoo/addons/pos_order_split_invoice/static/description/icon.png
odoo/addons/pos_order_split_invoice/static/description/index.html
odoo/addons/pos_order_split_invoice/static/src/app/store/pos_store.esm.js
odoo/addons/pos_order_split_invoice/static/src/generic_components/product_card.esm.js
odoo/addons/pos_order_split_invoice/static/src/generic_components/product_card.xml
odoo/addons/pos_order_split_invoice/static/src/models/order.esm.js
odoo/addons/pos_order_split_invoice/static/src/models/order_line.esm.js
odoo/addons/pos_order_split_invoice/static/src/models/product.esm.js
odoo/addons/pos_order_split_invoice/static/src/screens/product_screen/product_list.xml
odoo/addons/pos_order_split_invoice/static/tests/tours/TestSplitInvoice.esm.js
odoo/addons/pos_order_split_invoice/tests/__init__.py
odoo/addons/pos_order_split_invoice/tests/test_frontend.py
odoo/addons/pos_order_split_invoice/views/account_move.xml
odoo/addons/pos_order_split_invoice/views/pos_order.xml
odoo/addons/pos_order_split_invoice/views/pos_session.xml
odoo/addons/pos_order_split_invoice/views/product_pricelist.xml
odoo_addon_pos_order_split_invoice-17.0.1.0.0.8.dist-info/METADATA
odoo_addon_pos_order_split_invoice-17.0.1.0.0.8.dist-info/WHEEL
odoo_addon_pos_order_split_invoice-17.0.1.0.0.8.dist-info/top_level.txt
odoo_addon_pos_order_split_invoice-17.0.1.0.0.8.dist-info/RECORD
