Metadata-Version: 2.1
Name: odoo-addon-pos_order_split_invoice
Version: 17.0.1.0.0.8
Requires-Python: >=3.10
Requires-Dist: odoo>=17.0a,<17.1dev
Summary: Allow to generate a secondary invoice from a point of sale order for a second partner
Home-page: https://github.com/OCA/pos
License: AGPL-3
Author: Dixmit,INVITU,Odoo Community Association (OCA)
Author-email: support@odoo-community.org
Classifier: Programming Language :: Python
Classifier: Framework :: Odoo
Classifier: Framework :: Odoo :: 17.0
Classifier: License :: OSI Approved :: GNU Affero General Public License v3
Classifier: Development Status :: 3 - Alpha
